beelzecookie/__init__.py
beelzecookie/analyzer.py
beelzecookie/cli.py
beelzecookie/debug_test.py
beelzecookie/main.py
beelzecookie/payload_generator.py
beelzecookie/real_payload_maker.py
beelzecookie/recon.py
beelzecookie/reporter.py
beelzecookie/request_engine.py
beelzecookie/simple_test.py
beelzecookie/test_example.py
beelzecookie-1.0.3.dist-info/METADATA
beelzecookie-1.0.3.dist-info/WHEEL
beelzecookie-1.0.3.dist-info/entry_points.txt
beelzecookie-1.0.3.dist-info/top_level.txt
beelzecookie-1.0.3.dist-info/RECORD
