Metadata-Version: 2.4
Name: beelzecookie
Version: 1.0.3
Summary: Cookie Bomb Vulnerability Scanner I want to be a cookie.
Author: 0xbthn
Project-URL: Bug Reports, https://github.com/0xbthn/beelzecookie/issues
Project-URL: Source, https://github.com/0xbthn/beelzecookie
Project-URL: Documentation, https://github.com/0xbthn/beelzecookie#readme
Keywords: security vulnerability scanner cookie bomb dos web application testing
Classifier: Development Status :: 4 - Beta
Classifier: Intended Audience :: Information Technology
Classifier: License :: OSI Approved :: MIT License
Classifier: Operating System :: OS Independent
Classifier: Programming Language :: Python :: 3
Classifier: Programming Language :: Python :: 3.7
Classifier: Programming Language :: Python :: 3.8
Classifier: Programming Language :: Python :: 3.9
Classifier: Programming Language :: Python :: 3.10
Classifier: Programming Language :: Python :: 3.11
Classifier: Topic :: Security
Classifier: Topic :: Internet :: WWW/HTTP
Classifier: Topic :: Software Development :: Testing
Requires-Python: >=3.7
Requires-Dist: requests>=2.28.0
Requires-Dist: beautifulsoup4>=4.11.0
Requires-Dist: lxml>=4.9.0
Requires-Dist: urllib3>=1.26.0
Dynamic: author
Dynamic: classifier
Dynamic: description
Dynamic: description-content-type
Dynamic: keywords
Dynamic: project-url
Dynamic: requires-dist
Dynamic: requires-python
Dynamic: summary
